etc/mepo-cd.bash
etc/mepo-cd.csh
etc/mepo-cd.zsh
etc/mepo-completion.bash
etc/mepoconfig-example
mepo/__init__.py
mepo/__main__.py
mepo/component.py
mepo/git.py
mepo/registry.py
mepo/state.py
mepo/cmdline/__init__.py
mepo/cmdline/branch_parser.py
mepo/cmdline/config_parser.py
mepo/cmdline/parser.py
mepo/cmdline/stash_parser.py
mepo/cmdline/tag_parser.py
mepo/command/__init__.py
mepo/command/branch.py
mepo/command/branch_create.py
mepo/command/branch_delete.py
mepo/command/branch_list.py
mepo/command/changed-files.py
mepo/command/checkout-if-exists.py
mepo/command/checkout.py
mepo/command/clone.py
mepo/command/commit.py
mepo/command/compare.py
mepo/command/config.py
mepo/command/config_delete.py
mepo/command/config_get.py
mepo/command/config_print.py
mepo/command/config_set.py
mepo/command/develop.py
mepo/command/diff.py
mepo/command/fetch.py
mepo/command/init.py
mepo/command/list.py
mepo/command/pull-all.py
mepo/command/pull.py
mepo/command/push.py
mepo/command/reset.py
mepo/command/restore-state.py
mepo/command/save.py
mepo/command/stage.py
mepo/command/stash.py
mepo/command/stash_apply.py
mepo/command/stash_list.py
mepo/command/stash_pop.py
mepo/command/stash_push.py
mepo/command/stash_show.py
mepo/command/status.py
mepo/command/tag.py
mepo/command/tag_create.py
mepo/command/tag_delete.py
mepo/command/tag_list.py
mepo/command/tag_push.py
mepo/command/unstage.py
mepo/command/update-state.py
mepo/command/whereis.py
mepo/utilities/__init__.py
mepo/utilities/chdir.py
mepo/utilities/colors.py
mepo/utilities/exceptions.py
mepo/utilities/mepoconfig.py
mepo/utilities/shellcmd.py
mepo/utilities/statcolor.py
mepo/utilities/verify.py
mepo/utilities/version.py
mepo-2.4.0.dist-info/METADATA
mepo-2.4.0.dist-info/WHEEL
mepo-2.4.0.dist-info/entry_points.txt
mepo-2.4.0.dist-info/licenses/LICENSE
mepo-2.4.0.dist-info/licenses/LICENSE-NOSA
mepo-2.4.0.dist-info/RECORD
