Metadata-Version: 2.4
Name: mepo
Version: 2.4.0
Summary: A tool for managing (m)ultiple r(epo)s
Author-email: GMAO SI Team <siteam@gmao.gsfc.nasa.gov>
License-Expression: Apache-2.0
License-File: LICENSE
License-File: LICENSE-NOSA
Requires-Python: >=3.9
Requires-Dist: colorama>=0.4.6
Requires-Dist: pyyaml>=6.0.1
